{"type":"FeatureCollection","features":[{"type":"Feature","geometry":null,"properties":{"variable_name":"heatdegdays","name":"Blackstone","uid":null,"data":[{"season":"annual","values":[{"year":1960,"delta":6829.3,"range":"+6641.5 to +7050.1"},{"year":1970,"delta":6823.5,"range":"+6218.0 to +7207.0"},{"year":1980,"delta":6765.7,"range":"+6501.2 to +7141.8"},{"year":1990,"delta":6362.9,"range":"+5608.3 to +6895.1"},{"year":2000,"delta":6464.9,"range":"+6074.2 to +6850.1"}]},{"season":"fall","values":[{"year":1960,"delta":1313.1,"range":"+1133.1 to +1478.7"},{"year":1970,"delta":1376.8,"range":"+1198.1 to +1622.9"},{"year":1980,"delta":1383,"range":"+1248.5 to +1535.9"},{"year":1990,"delta":1325.5,"range":"+1147.5 to +1492.3"},{"year":2000,"delta":1236.6,"range":"+1094.6 to +1370.3"}]},{"season":"spring","values":[{"year":1960,"delta":1843.3,"range":"+1677.5 to +2200.5"},{"year":1970,"delta":1782.6,"range":"+1518.0 to +2012.5"},{"year":1980,"delta":1745.8,"range":"+1616.5 to +1996.3"},{"year":1990,"delta":1741.8,"range":"+1459.0 to +1943.1"},{"year":2000,"delta":1732.2,"range":"+1571.1 to +1919.0"}]},{"season":"summer","values":[{"year":1960,"delta":106.9,"range":"+62.4 to +165.3"},{"year":1970,"delta":108.3,"range":"+46.5 to +152.1"},{"year":1980,"delta":123,"range":"+61.8 to +197.8"},{"year":1990,"delta":77,"range":"+38.8 to +121.3"},{"year":2000,"delta":95.5,"range":"+61.8 to +130.2"}]},{"season":"winter","values":[{"year":1960,"delta":3566,"range":"+3337.0 to +3866.6"},{"year":1970,"delta":3555.8,"range":"+3226.7 to +3880.8"},{"year":1980,"delta":3513.9,"range":"+3233.1 to +3721.3"},{"year":1990,"delta":3218.7,"range":"+2797.3 to +3615.0"},{"year":2000,"delta":3400.6,"range":"+3045.2 to +3639.2"}]}]}},{"type":"Feature","geometry":null,"properties":{"variable_name":"heatdegdays","name":"Boston Harbor","uid":null,"data":[{"season":"annual","values":[{"year":1960,"delta":6374.3,"range":"+6173.2 to +6611.2"},{"year":1970,"delta":6188.8,"range":"+5660.8 to +6599.8"},{"year":1980,"delta":6183.3,"range":"+5936.2 to +6514.7"},{"year":1990,"delta":5863.8,"range":"+5228.1 to +6411.1"},{"year":2000,"delta":5995.2,"range":"+5563.4 to +6395.8"}]},{"season":"fall","values":[{"year":1960,"delta":1200.1,"range":"+1032.1 to +1344.2"},{"year":1970,"delta":1197.4,"range":"+969.4 to +1397.1"},{"year":1980,"delta":1207.5,"range":"+1062.7 to +1332.8"},{"year":1990,"delta":1162.1,"range":"+988.6 to +1345.7"},{"year":2000,"delta":1103,"range":"+940.3 to +1223.5"}]},{"season":"spring","values":[{"year":1960,"delta":1745.9,"range":"+1614.2 to +2071.7"},{"year":1970,"delta":1634.6,"range":"+1366.0 to +1881.9"},{"year":1980,"delta":1631.8,"range":"+1509.3 to +1874.7"},{"year":1990,"delta":1624.4,"range":"+1337.7 to +1860.0"},{"year":2000,"delta":1635.9,"range":"+1476.7 to +1828.1"}]},{"season":"summer","values":[{"year":1960,"delta":90,"range":"+49.5 to +144.9"},{"year":1970,"delta":77.1,"range":"+35.2 to +97.1"},{"year":1980,"delta":93.4,"range":"+35.1 to +167.8"},{"year":1990,"delta":60.6,"range":"+27.8 to +104.6"},{"year":2000,"delta":77.4,"range":"+36.8 to +105.3"}]},{"season":"winter","values":[{"year":1960,"delta":3338.3,"range":"+3132.6 to +3607.5"},{"year":1970,"delta":3279.7,"range":"+2975.9 to +3569.7"},{"year":1980,"delta":3250.5,"range":"+2965.4 to +3465.8"},{"year":1990,"delta":3016.6,"range":"+2659.5 to +3380.7"},{"year":2000,"delta":3178.8,"range":"+2825.2 to +3396.4"}]}]}},{"type":"Feature","geometry":null,"properties":{"variable_name":"heatdegdays","name":"Buzzards Bay","uid":null,"data":[{"season":"annual","values":[{"year":1960,"delta":6071.8,"range":"+5908.0 to +6334.0"},{"year":1970,"delta":5935.2,"range":"+5359.1 to +6453.3"},{"year":1980,"delta":6049.4,"range":"+5796.3 to +6400.6"},{"year":1990,"delta":5613.7,"range":"+5001.8 to +6170.1"},{"year":2000,"delta":5827,"range":"+5278.4 to +6289.2"}]},{"season":"fall","values":[{"year":1960,"delta":1102.7,"range":"+944.2 to +1250.8"},{"year":1970,"delta":1107.3,"range":"+846.0 to +1373.6"},{"year":1980,"delta":1134.2,"range":"+950.3 to +1277.7"},{"year":1990,"delta":1052.2,"range":"+913.0 to +1224.5"},{"year":2000,"delta":1035.5,"range":"+844.1 to +1144.0"}]},{"season":"spring","values":[{"year":1960,"delta":1723.9,"range":"+1588.2 to +2057.6"},{"year":1970,"delta":1638.2,"range":"+1433.9 to +1846.1"},{"year":1980,"delta":1672.7,"range":"+1532.9 to +1857.9"},{"year":1990,"delta":1627.1,"range":"+1353.1 to +1898.0"},{"year":2000,"delta":1659.5,"range":"+1479.4 to +1896.3"}]},{"season":"summer","values":[{"year":1960,"delta":68.1,"range":"+35.7 to +105.4"},{"year":1970,"delta":65.8,"range":"+22.4 to +92.5"},{"year":1980,"delta":86.4,"range":"+32.3 to +186.6"},{"year":1990,"delta":47.7,"range":"+17.1 to +100.3"},{"year":2000,"delta":74.2,"range":"+27.0 to +98.3"}]},{"season":"winter","values":[{"year":1960,"delta":3177.1,"range":"+2985.8 to +3442.8"},{"year":1970,"delta":3124,"range":"+2801.1 to +3402.8"},{"year":1980,"delta":3156,"range":"+2806.5 to +3391.8"},{"year":1990,"delta":2886.7,"range":"+2502.3 to +3224.2"},{"year":2000,"delta":3057.8,"range":"+2714.6 to +3305.5"}]}]}},{"type":"Feature","geometry":null,"properties":{"variable_name":"heatdegdays","name":"Cape Cod","uid":null,"data":[{"season":"annual","values":[{"year":1960,"delta":6246.4,"range":"+6034.2 to +6460.1"},{"year":1970,"delta":6057.3,"range":"+5626.8 to +6421.0"},{"year":1980,"delta":6075.7,"range":"+5708.3 to +6427.7"},{"year":1990,"delta":5736.9,"range":"+5182.8 to +6332.6"},{"year":2000,"delta":5755.3,"range":"+5339.1 to +6046.6"}]},{"season":"fall","values":[{"year":1960,"delta":1149.8,"range":"+975.3 to +1289.1"},{"year":1970,"delta":1126.7,"range":"+929.3 to +1342.6"},{"year":1980,"delta":1118.8,"range":"+937.0 to +1231.5"},{"year":1990,"delta":1069.4,"range":"+954.4 to +1212.6"},{"year":2000,"delta":1005,"range":"+889.2 to +1134.5"}]},{"season":"spring","values":[{"year":1960,"delta":1851.4,"range":"+1706.9 to +2170.1"},{"year":1970,"delta":1754.6,"range":"+1583.8 to +1936.3"},{"year":1980,"delta":1774.5,"range":"+1662.6 to +1896.7"},{"year":1990,"delta":1755.2,"range":"+1510.7 to +2022.6"},{"year":2000,"delta":1710.2,"range":"+1562.1 to +1896.9"}]},{"season":"summer","values":[{"year":1960,"delta":102.2,"range":"+64.1 to +136.6"},{"year":1970,"delta":94.3,"range":"+49.1 to +124.5"},{"year":1980,"delta":107.3,"range":"+35.0 to +204.0"},{"year":1990,"delta":80.3,"range":"+49.3 to +126.7"},{"year":2000,"delta":91.6,"range":"+34.2 to +123.0"}]},{"season":"winter","values":[{"year":1960,"delta":3143,"range":"+2937.7 to +3435.4"},{"year":1970,"delta":3081.7,"range":"+2799.7 to +3368.5"},{"year":1980,"delta":3075.1,"range":"+2695.4 to +3301.1"},{"year":1990,"delta":2832.1,"range":"+2469.0 to +3122.8"},{"year":2000,"delta":2948.6,"range":"+2666.9 to +3207.3"}]}]}},{"type":"Feature","geometry":null,"properties":{"variable_name":"heatdegdays","name":"Charles","uid":null,"data":[{"season":"annual","values":[{"year":1960,"delta":6468.7,"range":"+6306.9 to +6715.7"},{"year":1970,"delta":6474.9,"range":"+5882.5 to +6889.6"},{"year":1980,"delta":6452.6,"range":"+6219.1 to +6807.4"},{"year":1990,"delta":6058.8,"range":"+5341.6 to +6599.6"},{"year":2000,"delta":6165.7,"range":"+5787.9 to +6553.0"}]},{"season":"fall","values":[{"year":1960,"delta":1224.5,"range":"+1046.5 to +1372.5"},{"year":1970,"delta":1280.9,"range":"+1080.1 to +1492.6"},{"year":1980,"delta":1298,"range":"+1116.6 to +1470.9"},{"year":1990,"delta":1238.8,"range":"+1064.2 to +1411.5"},{"year":2000,"delta":1163.1,"range":"+1023.9 to +1282.1"}]},{"season":"spring","values":[{"year":1960,"delta":1745.3,"range":"+1586.7 to +2063.7"},{"year":1970,"delta":1688.4,"range":"+1429.0 to +1917.4"},{"year":1980,"delta":1666,"range":"+1510.2 to +1928.3"},{"year":1990,"delta":1655.1,"range":"+1382.6 to +1878.3"},{"year":2000,"delta":1654,"range":"+1492.6 to +1839.5"}]},{"season":"summer","values":[{"year":1960,"delta":88.4,"range":"+45.5 to +139.6"},{"year":1970,"delta":86.2,"range":"+36.3 to +113.8"},{"year":1980,"delta":105.4,"range":"+48.0 to +182.2"},{"year":1990,"delta":60.1,"range":"+21.2 to +96.0"},{"year":2000,"delta":80.3,"range":"+47.2 to +107.8"}]},{"season":"winter","values":[{"year":1960,"delta":3410.6,"range":"+3189.8 to +3698.3"},{"year":1970,"delta":3419.5,"range":"+3079.3 to +3709.0"},{"year":1980,"delta":3383.3,"range":"+3153.1 to +3583.5"},{"year":1990,"delta":3104.7,"range":"+2712.5 to +3489.1"},{"year":2000,"delta":3268.4,"range":"+2911.0 to +3481.7"}]}]}},{"type":"Feature","geometry":null,"properties":{"variable_name":"heatdegdays","name":"Chicopee","uid":null,"data":[{"season":"annual","values":[{"year":1960,"delta":7444.2,"range":"+7188.5 to +7655.9"},{"year":1970,"delta":7359.6,"range":"+6736.6 to +7811.4"},{"year":1980,"delta":7386.4,"range":"+7132.4 to +7680.4"},{"year":1990,"delta":7043.5,"range":"+6231.0 to +7626.7"},{"year":2000,"delta":7209.4,"range":"+6857.2 to +7734.2"}]},{"season":"fall","values":[{"year":1960,"delta":1480.2,"range":"+1242.8 to +1678.2"},{"year":1970,"delta":1521.2,"range":"+1340.1 to +1778.9"},{"year":1980,"delta":1562.4,"range":"+1420.8 to +1701.5"},{"year":1990,"delta":1518.1,"range":"+1314.6 to +1711.1"},{"year":2000,"delta":1451,"range":"+1319.4 to +1581.0"}]},{"season":"spring","values":[{"year":1960,"delta":1986.1,"range":"+1792.7 to +2349.5"},{"year":1970,"delta":1913.3,"range":"+1650.2 to +2144.2"},{"year":1980,"delta":1895,"range":"+1748.6 to +2182.0"},{"year":1990,"delta":1924.4,"range":"+1572.4 to +2168.9"},{"year":2000,"delta":1918.7,"range":"+1729.6 to +2120.3"}]},{"season":"summer","values":[{"year":1960,"delta":165.4,"range":"+91.5 to +253.0"},{"year":1970,"delta":157.7,"range":"+72.2 to +214.7"},{"year":1980,"delta":190.3,"range":"+124.9 to +262.8"},{"year":1990,"delta":135.1,"range":"+87.7 to +230.1"},{"year":2000,"delta":159.3,"range":"+85.5 to +196.4"}]},{"season":"winter","values":[{"year":1960,"delta":3812.5,"range":"+3581.2 to +4146.1"},{"year":1970,"delta":3767.4,"range":"+3444.1 to +4059.0"},{"year":1980,"delta":3738.8,"range":"+3447.9 to +3940.0"},{"year":1990,"delta":3465.9,"range":"+3016.0 to +3941.3"},{"year":2000,"delta":3680.4,"range":"+3327.9 to +3963.2"}]}]}},{"type":"Feature","geometry":null,"properties":{"variable_name":"heatdegdays","name":"Connecticut","uid":null,"data":[{"season":"annual","values":[{"year":1960,"delta":7304.5,"range":"+7050.8 to +7604.1"},{"year":1970,"delta":7086.1,"range":"+6510.3 to +7552.8"},{"year":1980,"delta":7100.1,"range":"+6919.2 to +7481.7"},{"year":1990,"delta":6927.9,"range":"+6102.3 to +7513.3"},{"year":2000,"delta":7043.9,"range":"+6723.2 to +7381.3"}]},{"season":"fall","values":[{"year":1960,"delta":1433.7,"range":"+1240.7 to +1663.4"},{"year":1970,"delta":1427.4,"range":"+1228.6 to +1645.9"},{"year":1980,"delta":1477.6,"range":"+1348.0 to +1631.6"},{"year":1990,"delta":1490.9,"range":"+1236.0 to +1670.8"},{"year":2000,"delta":1405.9,"range":"+1296.2 to +1509.4"}]},{"season":"spring","values":[{"year":1960,"delta":1932.8,"range":"+1697.6 to +2264.3"},{"year":1970,"delta":1826,"range":"+1554.0 to +2052.4"},{"year":1980,"delta":1802.2,"range":"+1631.6 to +2137.8"},{"year":1990,"delta":1865.1,"range":"+1464.0 to +2093.2"},{"year":2000,"delta":1852.3,"range":"+1653.9 to +2027.5"}]},{"season":"summer","values":[{"year":1960,"delta":134.8,"range":"+58.4 to +216.5"},{"year":1970,"delta":115.4,"range":"+48.9 to +164.0"},{"year":1980,"delta":147.7,"range":"+85.2 to +200.6"},{"year":1990,"delta":109.9,"range":"+68.0 to +196.7"},{"year":2000,"delta":125.3,"range":"+61.5 to +169.9"}]},{"season":"winter","values":[{"year":1960,"delta":3803.1,"range":"+3539.3 to +4149.0"},{"year":1970,"delta":3717.3,"range":"+3412.7 to +4025.8"},{"year":1980,"delta":3672.7,"range":"+3416.7 to +3880.0"},{"year":1990,"delta":3462,"range":"+3008.6 to +3979.6"},{"year":2000,"delta":3660.4,"range":"+3259.9 to +3882.8"}]}]}},{"type":"Feature","geometry":null,"properties":{"variable_name":"heatdegdays","name":"Deerfield","uid":null,"data":[{"season":"annual","values":[{"year":1960,"delta":8190.5,"range":"+7934.3 to +8481.5"},{"year":1970,"delta":7974.4,"range":"+7378.8 to +8435.2"},{"year":1980,"delta":7840.7,"range":"+7581.9 to +8166.2"},{"year":1990,"delta":7662.8,"range":"+6810.7 to +8273.1"},{"year":2000,"delta":7783.7,"range":"+7393.7 to +8127.2"}]},{"season":"fall","values":[{"year":1960,"delta":1670.8,"range":"+1431.6 to +1899.6"},{"year":1970,"delta":1661.5,"range":"+1461.0 to +1926.0"},{"year":1980,"delta":1665.7,"range":"+1500.6 to +1829.7"},{"year":1990,"delta":1687.8,"range":"+1446.2 to +1880.9"},{"year":2000,"delta":1609.2,"range":"+1516.4 to +1715.9"}]},{"season":"spring","values":[{"year":1960,"delta":2192.7,"range":"+1962.5 to +2536.9"},{"year":1970,"delta":2102,"range":"+1846.0 to +2338.6"},{"year":1980,"delta":2025.1,"range":"+1822.4 to +2310.3"},{"year":1990,"delta":2079.8,"range":"+1649.9 to +2365.0"},{"year":2000,"delta":2066.8,"range":"+1851.1 to +2270.6"}]},{"season":"summer","values":[{"year":1960,"delta":262.1,"range":"+156.0 to +352.5"},{"year":1970,"delta":216.3,"range":"+108.7 to +298.5"},{"year":1980,"delta":234.8,"range":"+163.1 to +326.1"},{"year":1990,"delta":193.7,"range":"+140.4 to +302.5"},{"year":2000,"delta":201.3,"range":"+112.5 to +280.1"}]},{"season":"winter","values":[{"year":1960,"delta":4064.9,"range":"+3821.3 to +4406.1"},{"year":1970,"delta":3994.7,"range":"+3712.1 to +4280.4"},{"year":1980,"delta":3915.1,"range":"+3612.2 to +4143.1"},{"year":1990,"delta":3701.5,"range":"+3238.4 to +4200.8"},{"year":2000,"delta":3906.4,"range":"+3490.7 to +4145.3"}]}]}},{"type":"Feature","geometry":null,"properties":{"variable_name":"heatdegdays","name":"Farmington","uid":null,"data":[{"season":"annual","values":[{"year":1960,"delta":8151.8,"range":"+7998.2 to +8382.7"},{"year":1970,"delta":8126.2,"range":"+7442.8 to +8656.4"},{"year":1980,"delta":7938.4,"range":"+7680.0 to +8253.8"},{"year":1990,"delta":7598.4,"range":"+6576.7 to +8291.1"},{"year":2000,"delta":7511,"range":"+6945.9 to +7869.3"}]},{"season":"fall","values":[{"year":1960,"delta":1673.6,"range":"+1453.9 to +1900.9"},{"year":1970,"delta":1703,"range":"+1515.5 to +2004.8"},{"year":1980,"delta":1695.4,"range":"+1563.0 to +1804.5"},{"year":1990,"delta":1673.8,"range":"+1465.7 to +1871.0"},{"year":2000,"delta":1570.4,"range":"+1455.4 to +1677.7"}]},{"season":"spring","values":[{"year":1960,"delta":2191.6,"range":"+1962.6 to +2525.3"},{"year":1970,"delta":2165.7,"range":"+1926.1 to +2387.0"},{"year":1980,"delta":2071.4,"range":"+1898.0 to +2356.9"},{"year":1990,"delta":2085.2,"range":"+1736.3 to +2296.6"},{"year":2000,"delta":1982.4,"range":"+1812.7 to +2242.9"}]},{"season":"summer","values":[{"year":1960,"delta":252,"range":"+136.0 to +355.9"},{"year":1970,"delta":234.5,"range":"+126.8 to +309.7"},{"year":1980,"delta":250.5,"range":"+186.8 to +342.4"},{"year":1990,"delta":195.9,"range":"+122.0 to +349.7"},{"year":2000,"delta":179.2,"range":"+104.8 to +247.6"}]},{"season":"winter","values":[{"year":1960,"delta":4034.6,"range":"+3760.9 to +4367.7"},{"year":1970,"delta":4023,"range":"+3705.6 to +4292.8"},{"year":1980,"delta":3921.1,"range":"+3587.9 to +4149.1"},{"year":1990,"delta":3643.5,"range":"+3152.6 to +4139.6"},{"year":2000,"delta":3779.1,"range":"+3298.6 to +4086.2"}]}]}},{"type":"Feature","geometry":null,"properties":{"variable_name":"heatdegdays","name":"French","uid":null,"data":[{"season":"annual","values":[{"year":1960,"delta":7237.8,"range":"+7023.5 to +7464.0"},{"year":1970,"delta":7168.2,"range":"+6478.1 to +7551.1"},{"year":1980,"delta":7117.2,"range":"+6848.0 to +7397.4"},{"year":1990,"delta":6663.4,"range":"+5903.4 to +7191.5"},{"year":2000,"delta":6819.9,"range":"+6413.2 to +7216.6"}]},{"season":"fall","values":[{"year":1960,"delta":1417.8,"range":"+1219.9 to +1590.3"},{"year":1970,"delta":1470.1,"range":"+1273.2 to +1793.7"},{"year":1980,"delta":1471.1,"range":"+1347.7 to +1600.0"},{"year":1990,"delta":1406,"range":"+1229.5 to +1569.7"},{"year":2000,"delta":1318.9,"range":"+1174.3 to +1459.1"}]},{"season":"spring","values":[{"year":1960,"delta":1948.3,"range":"+1787.4 to +2324.7"},{"year":1970,"delta":1875.4,"range":"+1626.2 to +2092.7"},{"year":1980,"delta":1840.8,"range":"+1737.9 to +2105.1"},{"year":1990,"delta":1832.5,"range":"+1521.1 to +2059.9"},{"year":2000,"delta":1843.9,"range":"+1663.7 to +2058.1"}]},{"season":"summer","values":[{"year":1960,"delta":144.4,"range":"+100.5 to +216.1"},{"year":1970,"delta":137.7,"range":"+59.1 to +196.1"},{"year":1980,"delta":152.9,"range":"+81.5 to +241.1"},{"year":1990,"delta":99.4,"range":"+64.9 to +157.0"},{"year":2000,"delta":119.2,"range":"+79.7 to +154.6"}]},{"season":"winter","values":[{"year":1960,"delta":3727.3,"range":"+3509.9 to +4037.2"},{"year":1970,"delta":3685,"range":"+3331.9 to +4000.7"},{"year":1980,"delta":3652.4,"range":"+3369.5 to +3844.0"},{"year":1990,"delta":3325.5,"range":"+2902.7 to +3725.7"},{"year":2000,"delta":3537.9,"range":"+3208.0 to +3798.5"}]}]}},{"type":"Feature","geometry":null,"properties":{"variable_name":"heatdegdays","name":"Housatonic","uid":null,"data":[{"season":"annual","values":[{"year":1960,"delta":7945.3,"range":"+7740.3 to +8161.0"},{"year":1970,"delta":7992.4,"range":"+7358.1 to +8468.8"},{"year":1980,"delta":7899.2,"range":"+7651.7 to +8194.5"},{"year":1990,"delta":7574.4,"range":"+6648.9 to +8116.9"},{"year":2000,"delta":7484.5,"range":"+7095.0 to +7872.4"}]},{"season":"fall","values":[{"year":1960,"delta":1623.3,"range":"+1404.9 to +1852.1"},{"year":1970,"delta":1681.9,"range":"+1484.3 to +1984.6"},{"year":1980,"delta":1695.8,"range":"+1529.0 to +1817.9"},{"year":1990,"delta":1670.7,"range":"+1455.1 to +1854.1"},{"year":2000,"delta":1538.2,"range":"+1402.5 to +1675.1"}]},{"season":"spring","values":[{"year":1960,"delta":2123.1,"range":"+1891.4 to +2451.6"},{"year":1970,"delta":2113.1,"range":"+1895.0 to +2365.4"},{"year":1980,"delta":2034.1,"range":"+1866.0 to +2321.8"},{"year":1990,"delta":2055.8,"range":"+1713.7 to +2305.5"},{"year":2000,"delta":1971,"range":"+1749.4 to +2203.4"}]},{"season":"summer","values":[{"year":1960,"delta":241.8,"range":"+125.1 to +330.4"},{"year":1970,"delta":232.1,"range":"+120.2 to +301.0"},{"year":1980,"delta":250.4,"range":"+185.7 to +351.8"},{"year":1990,"delta":183.1,"range":"+119.8 to +302.4"},{"year":2000,"delta":170.9,"range":"+81.0 to +240.4"}]},{"season":"winter","values":[{"year":1960,"delta":3957.1,"range":"+3678.2 to +4267.6"},{"year":1970,"delta":3965.4,"range":"+3676.3 to +4243.1"},{"year":1980,"delta":3918.9,"range":"+3591.6 to +4153.7"},{"year":1990,"delta":3664.7,"range":"+3201.9 to +4142.7"},{"year":2000,"delta":3804.4,"range":"+3369.1 to +4085.4"}]}]}},{"type":"Feature","geometry":null,"properties":{"variable_name":"heatdegdays","name":"Hudson","uid":null,"data":[{"season":"annual","values":[{"year":1960,"delta":8412.6,"range":"+8185.7 to +8640.8"},{"year":1970,"delta":8369.1,"range":"+7739.6 to +8818.5"},{"year":1980,"delta":8212.4,"range":"+7933.2 to +8484.0"},{"year":1990,"delta":7820.4,"range":"+6878.7 to +8367.8"},{"year":2000,"delta":7812.8,"range":"+7354.8 to +8200.7"}]},{"season":"fall","values":[{"year":1960,"delta":1730.1,"range":"+1498.7 to +1949.7"},{"year":1970,"delta":1768.6,"range":"+1534.5 to +2044.7"},{"year":1980,"delta":1756.1,"range":"+1552.3 to +1917.9"},{"year":1990,"delta":1722.2,"range":"+1494.6 to +1915.2"},{"year":2000,"delta":1607.2,"range":"+1421.4 to +1750.2"}]},{"season":"spring","values":[{"year":1960,"delta":2255.7,"range":"+2037.9 to +2601.8"},{"year":1970,"delta":2230.4,"range":"+1996.6 to +2494.7"},{"year":1980,"delta":2140.6,"range":"+1927.9 to +2430.7"},{"year":1990,"delta":2125,"range":"+1777.6 to +2415.6"},{"year":2000,"delta":2069.1,"range":"+1827.7 to +2288.3"}]},{"season":"summer","values":[{"year":1960,"delta":302.4,"range":"+181.0 to +407.1"},{"year":1970,"delta":293.5,"range":"+166.7 to +390.9"},{"year":1980,"delta":296.9,"range":"+237.7 to +411.9"},{"year":1990,"delta":210.2,"range":"+137.0 to +339.7"},{"year":2000,"delta":198.1,"range":"+98.4 to +287.6"}]},{"season":"winter","values":[{"year":1960,"delta":4124.4,"range":"+3833.0 to +4479.4"},{"year":1970,"delta":4076.6,"range":"+3800.0 to +4338.0"},{"year":1980,"delta":4018.7,"range":"+3665.9 to +4272.3"},{"year":1990,"delta":3763,"range":"+3305.9 to +4192.3"},{"year":2000,"delta":3938.4,"range":"+3496.9 to +4239.7"}]}]}},{"type":"Feature","geometry":null,"properties":{"variable_name":"heatdegdays","name":"Ipswich","uid":null,"data":[{"season":"annual","values":[{"year":1960,"delta":6518,"range":"+6186.7 to +6761.5"},{"year":1970,"delta":6343.1,"range":"+5847.0 to +6809.9"},{"year":1980,"delta":6386,"range":"+6064.7 to +6763.7"},{"year":1990,"delta":6078.6,"range":"+5315.4 to +6697.2"},{"year":2000,"delta":6103.3,"range":"+5703.2 to +6536.0"}]},{"season":"fall","values":[{"year":1960,"delta":1229.8,"range":"+1039.7 to +1387.1"},{"year":1970,"delta":1227.7,"range":"+1011.2 to +1417.2"},{"year":1980,"delta":1273.7,"range":"+1159.9 to +1407.5"},{"year":1990,"delta":1207.4,"range":"+997.5 to +1428.4"},{"year":2000,"delta":1128.5,"range":"+969.4 to +1260.1"}]},{"season":"spring","values":[{"year":1960,"delta":1789.3,"range":"+1670.6 to +2134.8"},{"year":1970,"delta":1681.8,"range":"+1433.8 to +1933.6"},{"year":1980,"delta":1686.2,"range":"+1523.6 to +1887.2"},{"year":1990,"delta":1700.6,"range":"+1432.6 to +1952.8"},{"year":2000,"delta":1663.7,"range":"+1492.0 to +1871.0"}]},{"season":"summer","values":[{"year":1960,"delta":96.5,"range":"+61.8 to +166.7"},{"year":1970,"delta":82.4,"range":"+43.5 to +102.6"},{"year":1980,"delta":109.4,"range":"+50.5 to +208.8"},{"year":1990,"delta":68.3,"range":"+29.2 to +102.7"},{"year":2000,"delta":78.9,"range":"+43.1 to +108.0"}]},{"season":"winter","values":[{"year":1960,"delta":3402.3,"range":"+3199.3 to +3692.7"},{"year":1970,"delta":3351.3,"range":"+3042.2 to +3614.2"},{"year":1980,"delta":3316.7,"range":"+3019.8 to +3528.3"},{"year":1990,"delta":3102.3,"range":"+2731.8 to +3503.7"},{"year":2000,"delta":3232.2,"range":"+2863.1 to +3484.9"}]}]}},{"type":"Feature","geometry":null,"properties":{"variable_name":"heatdegdays","name":"Marthas Vineyard","uid":null,"data":[{"season":"annual","values":[{"year":1960,"delta":6158,"range":"+5870.2 to +6438.1"},{"year":1970,"delta":5840.6,"range":"+5393.7 to +6267.2"},{"year":1980,"delta":5950.9,"range":"+5630.2 to +6252.4"},{"year":1990,"delta":5524.8,"range":"+4983.3 to +6141.4"},{"year":2000,"delta":5549.2,"range":"+5116.9 to +5906.0"}]},{"season":"fall","values":[{"year":1960,"delta":1075,"range":"+905.4 to +1210.5"},{"year":1970,"delta":1031.6,"range":"+816.9 to +1265.6"},{"year":1980,"delta":1089.6,"range":"+922.6 to +1199.1"},{"year":1990,"delta":1004,"range":"+822.2 to +1168.6"},{"year":2000,"delta":924,"range":"+774.2 to +1035.8"}]},{"season":"spring","values":[{"year":1960,"delta":1852.2,"range":"+1702.0 to +2139.1"},{"year":1970,"delta":1704,"range":"+1533.7 to +1888.3"},{"year":1980,"delta":1721.2,"range":"+1574.3 to +1859.3"},{"year":1990,"delta":1686.4,"range":"+1438.3 to +1983.8"},{"year":2000,"delta":1654.8,"range":"+1491.6 to +1845.6"}]},{"season":"summer","values":[{"year":1960,"delta":94.4,"range":"+70.9 to +115.8"},{"year":1970,"delta":73.9,"range":"+33.3 to +93.4"},{"year":1980,"delta":92.5,"range":"+20.4 to +214.0"},{"year":1990,"delta":62.6,"range":"+30.9 to +103.1"},{"year":2000,"delta":78.3,"range":"+32.9 to +100.7"}]},{"season":"winter","values":[{"year":1960,"delta":3136.5,"range":"+2886.3 to +3402.0"},{"year":1970,"delta":3031.1,"range":"+2729.5 to +3336.2"},{"year":1980,"delta":3047.6,"range":"+2682.9 to +3260.3"},{"year":1990,"delta":2771.8,"range":"+2411.0 to +3043.3"},{"year":2000,"delta":2892.1,"range":"+2578.5 to +3137.4"}]}]}},{"type":"Feature","geometry":null,"properties":{"variable_name":"heatdegdays","name":"Merrimack","uid":null,"data":[{"season":"annual","values":[{"year":1960,"delta":6579.6,"range":"+6309.4 to +6838.9"},{"year":1970,"delta":6665.7,"range":"+6231.1 to +7092.4"},{"year":1980,"delta":6868.3,"range":"+6534.1 to +7181.3"},{"year":1990,"delta":6543.9,"range":"+5764.3 to +7067.3"},{"year":2000,"delta":6599,"range":"+6277.0 to +6968.3"}]},{"season":"fall","values":[{"year":1960,"delta":1258.2,"range":"+1057.8 to +1432.6"},{"year":1970,"delta":1340.2,"range":"+1168.7 to +1530.8"},{"year":1980,"delta":1419.5,"range":"+1287.5 to +1568.6"},{"year":1990,"delta":1362.3,"range":"+1162.9 to +1551.7"},{"year":2000,"delta":1278.4,"range":"+1165.0 to +1390.0"}]},{"season":"spring","values":[{"year":1960,"delta":1759.3,"range":"+1611.1 to +2106.6"},{"year":1970,"delta":1719.9,"range":"+1477.5 to +1980.8"},{"year":1980,"delta":1782.6,"range":"+1620.1 to +1992.2"},{"year":1990,"delta":1791.1,"range":"+1495.1 to +2002.0"},{"year":2000,"delta":1769.2,"range":"+1608.9 to +1963.7"}]},{"season":"summer","values":[{"year":1960,"delta":80,"range":"+51.1 to +141.2"},{"year":1970,"delta":94.6,"range":"+54.8 to +123.4"},{"year":1980,"delta":137.9,"range":"+74.6 to +233.0"},{"year":1990,"delta":81.2,"range":"+38.9 to +122.5"},{"year":2000,"delta":94.3,"range":"+67.7 to +123.7"}]},{"season":"winter","values":[{"year":1960,"delta":3482.1,"range":"+3298.5 to +3778.2"},{"year":1970,"delta":3511,"range":"+3218.3 to +3725.2"},{"year":1980,"delta":3528.3,"range":"+3241.1 to +3714.7"},{"year":1990,"delta":3309.4,"range":"+2896.7 to +3744.2"},{"year":2000,"delta":3457.1,"range":"+3088.4 to +3693.2"}]}]}},{"type":"Feature","geometry":null,"properties":{"variable_name":"heatdegdays","name":"Millers","uid":null,"data":[{"season":"annual","values":[{"year":1960,"delta":7811.8,"range":"+7603.1 to +8045.2"},{"year":1970,"delta":7900,"range":"+7251.7 to +8380.6"},{"year":1980,"delta":7893.1,"range":"+7514.9 to +8166.3"},{"year":1990,"delta":7431.1,"range":"+6610.7 to +8005.2"},{"year":2000,"delta":7618.3,"range":"+7231.7 to +8101.1"}]},{"season":"fall","values":[{"year":1960,"delta":1584.5,"range":"+1348.5 to +1781.0"},{"year":1970,"delta":1670.2,"range":"+1504.1 to +1950.7"},{"year":1980,"delta":1692.9,"range":"+1539.8 to +1862.0"},{"year":1990,"delta":1617.3,"range":"+1437.1 to +1812.8"},{"year":2000,"delta":1566.3,"range":"+1469.6 to +1628.7"}]},{"season":"spring","values":[{"year":1960,"delta":2070.3,"range":"+1870.6 to +2444.3"},{"year":1970,"delta":2042.8,"range":"+1806.6 to +2279.6"},{"year":1980,"delta":2018.2,"range":"+1866.4 to +2277.7"},{"year":1990,"delta":2016.6,"range":"+1701.8 to +2269.8"},{"year":2000,"delta":2015.8,"range":"+1820.7 to +2231.5"}]},{"season":"summer","values":[{"year":1960,"delta":194.4,"range":"+97.2 to +288.8"},{"year":1970,"delta":200.3,"range":"+101.2 to +270.5"},{"year":1980,"delta":242.5,"range":"+175.5 to +329.5"},{"year":1990,"delta":152.4,"range":"+95.7 to +263.4"},{"year":2000,"delta":174.7,"range":"+93.4 to +234.1"}]},{"season":"winter","values":[{"year":1960,"delta":3962.5,"range":"+3718.3 to +4293.6"},{"year":1970,"delta":3986.7,"range":"+3670.1 to +4249.2"},{"year":1980,"delta":3939.5,"range":"+3644.2 to +4138.4"},{"year":1990,"delta":3644.7,"range":"+3188.4 to +4119.0"},{"year":2000,"delta":3861.5,"range":"+3451.5 to +4136.2"}]}]}},{"type":"Feature","geometry":null,"properties":{"variable_name":"heatdegdays","name":"Nantucket","uid":null,"data":[{"season":"annual","values":[{"year":1960,"delta":6249.7,"range":"+5955.8 to +6490.5"},{"year":1970,"delta":5946.4,"range":"+5486.6 to +6389.7"},{"year":1980,"delta":5784,"range":"+5653.0 to +6001.1"},{"year":1990,"delta":5795.7,"range":"+5708.8 to +5884.4"},{"year":2000,"delta":5779.3,"range":"+5284.6 to +5925.8"}]},{"season":"fall","values":[{"year":1960,"delta":1133,"range":"+951.6 to +1297.9"},{"year":1970,"delta":1054.9,"range":"+728.7 to +1233.2"},{"year":1980,"delta":1040.2,"range":"+912.9 to +1188.7"},{"year":1990,"delta":1052.1,"range":"+915.1 to +1160.9"},{"year":2000,"delta":935.7,"range":"+842.1 to +1035.0"}]},{"season":"spring","values":[{"year":1960,"delta":1962.6,"range":"+1831.8 to +2262.5"},{"year":1970,"delta":1783.3,"range":"+1605.8 to +1975.3"},{"year":1980,"delta":1750.3,"range":"+1633.9 to +1928.3"},{"year":1990,"delta":1787.7,"range":"+1700.9 to +1853.3"},{"year":2000,"delta":1769.1,"range":"+1544.4 to +1897.0"}]},{"season":"summer","values":[{"year":1960,"delta":160.6,"range":"+112.8 to +217.0"},{"year":1970,"delta":148.9,"range":"+101.0 to +225.0"},{"year":1980,"delta":94.7,"range":"+69.9 to +125.6"},{"year":1990,"delta":75.5,"range":"+48.7 to +121.0"},{"year":2000,"delta":105.3,"range":"+90.8 to +115.1"}]},{"season":"winter","values":[{"year":1960,"delta":2968.3,"range":"+2788.8 to +3134.0"},{"year":1970,"delta":2885.5,"range":"+2653.3 to +3170.8"},{"year":1980,"delta":2895,"range":"+2658.4 to +3120.3"},{"year":1990,"delta":2903.8,"range":"+2752.1 to +3034.1"},{"year":2000,"delta":3030.9,"range":"+2909.1 to +3149.8"}]}]}},{"type":"Feature","geometry":null,"properties":{"variable_name":"heatdegdays","name":"Narragansett Bay","uid":null,"data":[{"season":"annual","values":[{"year":1960,"delta":6101.8,"range":"+5916.8 to +6373.3"},{"year":1970,"delta":6061.9,"range":"+5493.6 to +6678.1"},{"year":1980,"delta":6097.2,"range":"+5831.9 to +6483.1"},{"year":1990,"delta":5683.5,"range":"+5073.6 to +6117.2"},{"year":2000,"delta":5915.2,"range":"+5507.3 to +6275.2"}]},{"season":"fall","values":[{"year":1960,"delta":1128.9,"range":"+963.8 to +1276.8"},{"year":1970,"delta":1182.3,"range":"+963.0 to +1467.3"},{"year":1980,"delta":1195.8,"range":"+1022.8 to +1380.7"},{"year":1990,"delta":1129.7,"range":"+954.9 to +1306.7"},{"year":2000,"delta":1095.6,"range":"+952.1 to +1193.2"}]},{"season":"spring","values":[{"year":1960,"delta":1681.8,"range":"+1553.6 to +2017.2"},{"year":1970,"delta":1610.4,"range":"+1418.7 to +1824.1"},{"year":1980,"delta":1604.6,"range":"+1507.6 to +1813.4"},{"year":1990,"delta":1570.9,"range":"+1295.8 to +1779.0"},{"year":2000,"delta":1614.4,"range":"+1465.8 to +1823.7"}]},{"season":"summer","values":[{"year":1960,"delta":64.3,"range":"+28.1 to +113.7"},{"year":1970,"delta":72.2,"range":"+26.7 to +107.3"},{"year":1980,"delta":84.7,"range":"+34.8 to +173.2"},{"year":1990,"delta":45.3,"range":"+17.6 to +91.9"},{"year":2000,"delta":65.5,"range":"+31.8 to +91.5"}]},{"season":"winter","values":[{"year":1960,"delta":3226.8,"range":"+3027.6 to +3491.8"},{"year":1970,"delta":3197,"range":"+2895.1 to +3465.4"},{"year":1980,"delta":3212.1,"range":"+2935.8 to +3414.9"},{"year":1990,"delta":2937.6,"range":"+2572.4 to +3300.1"},{"year":2000,"delta":3139.8,"range":"+2813.8 to +3355.3"}]}]}},{"type":"Feature","geometry":null,"properties":{"variable_name":"heatdegdays","name":"Nashua","uid":null,"data":[{"season":"annual","values":[{"year":1960,"delta":7167.6,"range":"+6934.7 to +7441.8"},{"year":1970,"delta":7153.9,"range":"+6630.5 to +7588.1"},{"year":1980,"delta":7230.7,"range":"+6917.3 to +7572.2"},{"year":1990,"delta":6890.8,"range":"+6056.9 to +7434.8"},{"year":2000,"delta":7054.8,"range":"+6701.0 to +7570.6"}]},{"season":"fall","values":[{"year":1960,"delta":1399.9,"range":"+1198.9 to +1573.0"},{"year":1970,"delta":1471.3,"range":"+1290.8 to +1714.2"},{"year":1980,"delta":1512.1,"range":"+1375.1 to +1660.8"},{"year":1990,"delta":1466.9,"range":"+1283.6 to +1647.4"},{"year":2000,"delta":1409.3,"range":"+1287.2 to +1526.5"}]},{"season":"spring","values":[{"year":1960,"delta":1933.8,"range":"+1758.0 to +2306.6"},{"year":1970,"delta":1862.4,"range":"+1588.2 to +2119.9"},{"year":1980,"delta":1862.8,"range":"+1700.5 to +2100.5"},{"year":1990,"delta":1879.4,"range":"+1563.1 to +2089.2"},{"year":2000,"delta":1880.5,"range":"+1696.6 to +2092.7"}]},{"season":"summer","values":[{"year":1960,"delta":130,"range":"+90.4 to +196.1"},{"year":1970,"delta":137,"range":"+71.8 to +190.9"},{"year":1980,"delta":167.5,"range":"+96.3 to +254.9"},{"year":1990,"delta":111.4,"range":"+63.8 to +184.3"},{"year":2000,"delta":137.4,"range":"+81.9 to +167.7"}]},{"season":"winter","values":[{"year":1960,"delta":3703.9,"range":"+3507.1 to +4007.6"},{"year":1970,"delta":3683.3,"range":"+3385.0 to +3968.0"},{"year":1980,"delta":3688.2,"range":"+3424.9 to +3889.9"},{"year":1990,"delta":3433.2,"range":"+2984.2 to +3885.2"},{"year":2000,"delta":3627.6,"range":"+3262.4 to +3902.5"}]}]}},{"type":"Feature","geometry":null,"properties":{"variable_name":"heatdegdays","name":"North Coastal","uid":null,"data":[{"season":"annual","values":[{"year":1960,"delta":6496.3,"range":"+6249.9 to +6743.7"},{"year":1970,"delta":6308.6,"range":"+5849.0 to +6731.0"},{"year":1980,"delta":6268.6,"range":"+5962.7 to +6724.7"},{"year":1990,"delta":6004.3,"range":"+5236.1 to +6697.7"},{"year":2000,"delta":6050.2,"range":"+5591.8 to +6520.7"}]},{"season":"fall","values":[{"year":1960,"delta":1226,"range":"+1054.3 to +1366.3"},{"year":1970,"delta":1216.8,"range":"+1006.6 to +1413.3"},{"year":1980,"delta":1236.3,"range":"+1119.3 to +1376.6"},{"year":1990,"delta":1180.9,"range":"+972.0 to +1413.9"},{"year":2000,"delta":1108.5,"range":"+937.7 to +1228.2"}]},{"season":"spring","values":[{"year":1960,"delta":1805.8,"range":"+1682.1 to +2139.9"},{"year":1970,"delta":1692.5,"range":"+1439.4 to +1949.4"},{"year":1980,"delta":1667.1,"range":"+1519.0 to +1859.2"},{"year":1990,"delta":1690.4,"range":"+1427.9 to +1961.8"},{"year":2000,"delta":1667.8,"range":"+1489.6 to +1876.2"}]},{"season":"summer","values":[{"year":1960,"delta":101.7,"range":"+65.1 to +159.7"},{"year":1970,"delta":89.6,"range":"+49.7 to +111.7"},{"year":1980,"delta":103.4,"range":"+46.7 to +203.9"},{"year":1990,"delta":68.5,"range":"+30.9 to +112.0"},{"year":2000,"delta":82.3,"range":"+40.1 to +112.0"}]},{"season":"winter","values":[{"year":1960,"delta":3362.8,"range":"+3166.7 to +3650.1"},{"year":1970,"delta":3309.7,"range":"+3019.3 to +3574.6"},{"year":1980,"delta":3261.8,"range":"+2962.0 to +3509.4"},{"year":1990,"delta":3064.5,"range":"+2671.5 to +3456.4"},{"year":2000,"delta":3191.6,"range":"+2822.8 to +3444.8"}]}]}},{"type":"Feature","geometry":null,"properties":{"variable_name":"heatdegdays","name":"Parker","uid":null,"data":[{"season":"annual","values":[{"year":1960,"delta":6344.5,"range":"+6138.7 to +6586.5"},{"year":1970,"delta":6204,"range":"+5763.6 to +6605.4"},{"year":1980,"delta":6573.3,"range":"+6231.7 to +6858.8"},{"year":1990,"delta":6304.3,"range":"+5540.5 to +6876.3"},{"year":2000,"delta":6347.9,"range":"+5988.3 to +6749.0"}]},{"season":"fall","values":[{"year":1960,"delta":1182.4,"range":"+1001.4 to +1316.5"},{"year":1970,"delta":1188.2,"range":"+987.0 to +1372.5"},{"year":1980,"delta":1327.2,"range":"+1192.5 to +1462.8"},{"year":1990,"delta":1289.2,"range":"+1081.8 to +1503.6"},{"year":2000,"delta":1211.7,"range":"+1080.0 to +1342.6"}]},{"season":"spring","values":[{"year":1960,"delta":1719.5,"range":"+1580.5 to +2062.8"},{"year":1970,"delta":1622.6,"range":"+1378.6 to +1874.8"},{"year":1980,"delta":1739,"range":"+1560.2 to +1948.0"},{"year":1990,"delta":1749.8,"range":"+1466.7 to +1980.7"},{"year":2000,"delta":1716.6,"range":"+1550.0 to +1915.7"}]},{"season":"summer","values":[{"year":1960,"delta":71.1,"range":"+45.6 to +127.9"},{"year":1970,"delta":63.9,"range":"+35.0 to +83.4"},{"year":1980,"delta":123.6,"range":"+59.6 to +218.7"},{"year":1990,"delta":77.1,"range":"+36.3 to +112.2"},{"year":2000,"delta":89.1,"range":"+55.0 to +122.4"}]},{"season":"winter","values":[{"year":1960,"delta":3371.5,"range":"+3174.5 to +3655.5"},{"year":1970,"delta":3329.4,"range":"+3035.6 to +3577.6"},{"year":1980,"delta":3383.5,"range":"+3106.7 to +3564.3"},{"year":1990,"delta":3188.3,"range":"+2806.7 to +3609.5"},{"year":2000,"delta":3330.5,"range":"+2965.8 to +3575.2"}]}]}},{"type":"Feature","geometry":null,"properties":{"variable_name":"heatdegdays","name":"Quinebaug","uid":null,"data":[{"season":"annual","values":[{"year":1960,"delta":7342,"range":"+7056.5 to +7588.1"},{"year":1970,"delta":7186.9,"range":"+6502.7 to +7618.7"},{"year":1980,"delta":7165.9,"range":"+6866.1 to +7425.1"},{"year":1990,"delta":6802.2,"range":"+6068.7 to +7325.9"},{"year":2000,"delta":6937.8,"range":"+6585.3 to +7252.3"}]},{"season":"fall","values":[{"year":1960,"delta":1454,"range":"+1228.2 to +1609.5"},{"year":1970,"delta":1470.3,"range":"+1293.9 to +1731.8"},{"year":1980,"delta":1493.1,"range":"+1365.7 to +1614.6"},{"year":1990,"delta":1445,"range":"+1262.6 to +1611.5"},{"year":2000,"delta":1354.2,"range":"+1214.7 to +1486.6"}]},{"season":"spring","values":[{"year":1960,"delta":1966.9,"range":"+1791.6 to +2336.2"},{"year":1970,"delta":1873.3,"range":"+1627.5 to +2103.2"},{"year":1980,"delta":1837.5,"range":"+1717.7 to +2084.7"},{"year":1990,"delta":1872.1,"range":"+1557.2 to +2086.4"},{"year":2000,"delta":1871.3,"range":"+1718.4 to +2074.5"}]},{"season":"summer","values":[{"year":1960,"delta":151.7,"range":"+105.7 to +240.0"},{"year":1970,"delta":132.1,"range":"+56.1 to +187.4"},{"year":1980,"delta":156.8,"range":"+87.3 to +229.7"},{"year":1990,"delta":114,"range":"+79.6 to +182.8"},{"year":2000,"delta":133.5,"range":"+92.8 to +176.6"}]},{"season":"winter","values":[{"year":1960,"delta":3769.4,"range":"+3568.1 to +4095.8"},{"year":1970,"delta":3711.2,"range":"+3343.8 to +4027.0"},{"year":1980,"delta":3678.5,"range":"+3385.2 to +3891.3"},{"year":1990,"delta":3371.1,"range":"+2941.0 to +3803.1"},{"year":2000,"delta":3578.8,"range":"+3241.4 to +3820.8"}]}]}},{"type":"Feature","geometry":null,"properties":{"variable_name":"heatdegdays","name":"Shawsheen","uid":null,"data":[{"season":"annual","values":[{"year":1960,"delta":6676.9,"range":"+6295.6 to +6972.8"},{"year":1970,"delta":6533.5,"range":"+6000.5 to +6991.4"},{"year":1980,"delta":6579.4,"range":"+6255.5 to +6911.6"},{"year":1990,"delta":6258.9,"range":"+5506.1 to +6836.4"},{"year":2000,"delta":6343.8,"range":"+6004.6 to +6712.9"}]},{"season":"fall","values":[{"year":1960,"delta":1292.6,"range":"+1060.3 to +1460.3"},{"year":1970,"delta":1305.8,"range":"+1101.9 to +1496.7"},{"year":1980,"delta":1350.3,"range":"+1229.2 to +1474.7"},{"year":1990,"delta":1295.4,"range":"+1096.1 to +1502.1"},{"year":2000,"delta":1216.1,"range":"+1083.0 to +1331.9"}]},{"season":"spring","values":[{"year":1960,"delta":1797,"range":"+1650.7 to +2138.7"},{"year":1970,"delta":1704.5,"range":"+1469.5 to +1953.3"},{"year":1980,"delta":1703.4,"range":"+1561.5 to +1932.9"},{"year":1990,"delta":1703.4,"range":"+1423.8 to +1925.7"},{"year":2000,"delta":1700.9,"range":"+1527.6 to +1895.2"}]},{"season":"summer","values":[{"year":1960,"delta":102,"range":"+53.2 to +168.9"},{"year":1970,"delta":93.1,"range":"+47.2 to +116.4"},{"year":1980,"delta":120.7,"range":"+54.7 to +204.1"},{"year":1990,"delta":71.5,"range":"+26.9 to +109.8"},{"year":2000,"delta":85.9,"range":"+53.9 to +116.7"}]},{"season":"winter","values":[{"year":1960,"delta":3485.3,"range":"+3281.3 to +3778.4"},{"year":1970,"delta":3430.1,"range":"+3124.8 to +3710.4"},{"year":1980,"delta":3405,"range":"+3117.8 to +3591.7"},{"year":1990,"delta":3188.6,"range":"+2804.4 to +3584.4"},{"year":2000,"delta":3340.9,"range":"+2963.8 to +3577.4"}]}]}},{"type":"Feature","geometry":null,"properties":{"variable_name":"heatdegdays","name":"South Coastal","uid":null,"data":[{"season":"annual","values":[{"year":1960,"delta":6317.1,"range":"+5992.9 to +6752.3"},{"year":1970,"delta":6361.2,"range":"+5811.5 to +6842.4"},{"year":1980,"delta":6330,"range":"+6027.5 to +6707.8"},{"year":1990,"delta":5749.9,"range":"+5158.2 to +6283.1"},{"year":2000,"delta":5930.2,"range":"+5470.4 to +6379.5"}]},{"season":"fall","values":[{"year":1960,"delta":1198.4,"range":"+995.2 to +1366.5"},{"year":1970,"delta":1247.9,"range":"+1055.6 to +1459.8"},{"year":1980,"delta":1231.4,"range":"+1075.2 to +1361.1"},{"year":1990,"delta":1119.3,"range":"+944.6 to +1292.7"},{"year":2000,"delta":1090.2,"range":"+963.9 to +1197.5"}]},{"season":"spring","values":[{"year":1960,"delta":1775.3,"range":"+1617.1 to +2157.1"},{"year":1970,"delta":1736.2,"range":"+1527.5 to +1959.9"},{"year":1980,"delta":1738.9,"range":"+1615.7 to +1933.9"},{"year":1990,"delta":1648,"range":"+1370.5 to +1886.0"},{"year":2000,"delta":1663.1,"range":"+1490.6 to +1879.1"}]},{"season":"summer","values":[{"year":1960,"delta":94.9,"range":"+49.1 to +144.2"},{"year":1970,"delta":99.1,"range":"+45.2 to +127.9"},{"year":1980,"delta":113.9,"range":"+50.9 to +207.0"},{"year":1990,"delta":68.4,"range":"+38.1 to +119.7"},{"year":2000,"delta":81.8,"range":"+43.4 to +105.8"}]},{"season":"winter","values":[{"year":1960,"delta":3248.4,"range":"+3096.3 to +3594.1"},{"year":1970,"delta":3278,"range":"+2971.7 to +3560.2"},{"year":1980,"delta":3245.8,"range":"+2912.4 to +3475.8"},{"year":1990,"delta":2914.1,"range":"+2568.3 to +3226.5"},{"year":2000,"delta":3095.2,"range":"+2784.3 to +3324.0"}]}]}},{"type":"Feature","geometry":null,"properties":{"variable_name":"heatdegdays","name":"SuAsCo","uid":null,"data":[{"season":"annual","values":[{"year":1960,"delta":6674.9,"range":"+6380.2 to +6960.9"},{"year":1970,"delta":6641.5,"range":"+6130.6 to +7080.0"},{"year":1980,"delta":6651.6,"range":"+6387.1 to +7028.4"},{"year":1990,"delta":6310.9,"range":"+5487.7 to +6863.2"},{"year":2000,"delta":6481.6,"range":"+6138.3 to +6838.4"}]},{"season":"fall","values":[{"year":1960,"delta":1276.9,"range":"+1081.3 to +1450.9"},{"year":1970,"delta":1336.2,"range":"+1153.2 to +1530.8"},{"year":1980,"delta":1363.8,"range":"+1213.6 to +1535.7"},{"year":1990,"delta":1312.5,"range":"+1138.6 to +1486.6"},{"year":2000,"delta":1256.2,"range":"+1136.5 to +1356.7"}]},{"season":"spring","values":[{"year":1960,"delta":1786.8,"range":"+1636.4 to +2125.3"},{"year":1970,"delta":1714.1,"range":"+1443.1 to +1966.8"},{"year":1980,"delta":1691.9,"range":"+1528.8 to +1944.7"},{"year":1990,"delta":1699.3,"range":"+1406.0 to +1925.1"},{"year":2000,"delta":1719.5,"range":"+1562.3 to +1890.6"}]},{"season":"summer","values":[{"year":1960,"delta":87.9,"range":"+45.8 to +138.4"},{"year":1970,"delta":90.7,"range":"+43.0 to +130.7"},{"year":1980,"delta":111.9,"range":"+56.6 to +191.4"},{"year":1990,"delta":65.1,"range":"+25.3 to +98.3"},{"year":2000,"delta":89.3,"range":"+55.4 to +113.0"}]},{"season":"winter","values":[{"year":1960,"delta":3523.3,"range":"+3300.8 to +3823.0"},{"year":1970,"delta":3500.5,"range":"+3194.3 to +3799.6"},{"year":1980,"delta":3484,"range":"+3230.9 to +3666.2"},{"year":1990,"delta":3234,"range":"+2794.1 to +3659.2"},{"year":2000,"delta":3416.6,"range":"+3036.4 to +3620.8"}]}]}},{"type":"Feature","geometry":null,"properties":{"variable_name":"heatdegdays","name":"Taunton","uid":null,"data":[{"season":"annual","values":[{"year":1960,"delta":6417.5,"range":"+6050.8 to +6743.7"},{"year":1970,"delta":6332,"range":"+5799.6 to +6819.9"},{"year":1980,"delta":6244.3,"range":"+6006.3 to +6639.4"},{"year":1990,"delta":5813.5,"range":"+5202.6 to +6281.2"},{"year":2000,"delta":6024.2,"range":"+5566.8 to +6400.9"}]},{"season":"fall","values":[{"year":1960,"delta":1239.5,"range":"+1014.7 to +1397.2"},{"year":1970,"delta":1265.5,"range":"+1068.8 to +1490.3"},{"year":1980,"delta":1236.9,"range":"+1064.2 to +1406.6"},{"year":1990,"delta":1169.6,"range":"+986.1 to +1351.6"},{"year":2000,"delta":1132.7,"range":"+971.8 to +1234.0"}]},{"season":"spring","values":[{"year":1960,"delta":1767.8,"range":"+1638.2 to +2115.9"},{"year":1970,"delta":1690.8,"range":"+1488.0 to +1910.9"},{"year":1980,"delta":1655,"range":"+1550.3 to +1863.2"},{"year":1990,"delta":1612.5,"range":"+1321.2 to +1827.9"},{"year":2000,"delta":1648.2,"range":"+1479.9 to +1862.3"}]},{"season":"summer","values":[{"year":1960,"delta":96.2,"range":"+43.3 to +158.1"},{"year":1970,"delta":96.7,"range":"+40.7 to +125.8"},{"year":1980,"delta":98.2,"range":"+47.1 to +194.3"},{"year":1990,"delta":58.5,"range":"+28.6 to +106.5"},{"year":2000,"delta":77.6,"range":"+39.5 to +104.4"}]},{"season":"winter","values":[{"year":1960,"delta":3313.9,"range":"+3146.5 to +3611.7"},{"year":1970,"delta":3279.1,"range":"+2987.0 to +3560.6"},{"year":1980,"delta":3254.3,"range":"+2964.7 to +3464.4"},{"year":1990,"delta":2972.9,"range":"+2614.6 to +3326.0"},{"year":2000,"delta":3165.8,"range":"+2838.8 to +3401.5"}]}]}},{"type":"Feature","geometry":null,"properties":{"variable_name":"heatdegdays","name":"Ten Mile","uid":null,"data":[{"season":"annual","values":[{"year":1960,"delta":6508,"range":"+6306.9 to +6745.9"},{"year":1970,"delta":6434.1,"range":"+5841.8 to +6965.3"},{"year":1980,"delta":6388.8,"range":"+6183.0 to +6755.6"},{"year":1990,"delta":5963.6,"range":"+5298.0 to +6429.4"},{"year":2000,"delta":6170.8,"range":"+5797.3 to +6542.1"}]},{"season":"fall","values":[{"year":1960,"delta":1256.2,"range":"+1058.0 to +1416.9"},{"year":1970,"delta":1295,"range":"+1101.1 to +1531.1"},{"year":1980,"delta":1297.9,"range":"+1121.5 to +1459.0"},{"year":1990,"delta":1229.8,"range":"+1054.7 to +1388.5"},{"year":2000,"delta":1180.3,"range":"+1043.7 to +1287.0"}]},{"season":"spring","values":[{"year":1960,"delta":1766,"range":"+1629.6 to +2095.2"},{"year":1970,"delta":1688.6,"range":"+1462.1 to +1909.5"},{"year":1980,"delta":1657.5,"range":"+1548.4 to +1891.4"},{"year":1990,"delta":1631.3,"range":"+1359.4 to +1839.4"},{"year":2000,"delta":1659.4,"range":"+1517.6 to +1872.0"}]},{"season":"summer","values":[{"year":1960,"delta":100,"range":"+52.8 to +163.0"},{"year":1970,"delta":94.1,"range":"+34.3 to +129.5"},{"year":1980,"delta":107.1,"range":"+54.4 to +204.0"},{"year":1990,"delta":57.6,"range":"+23.7 to +99.9"},{"year":2000,"delta":77.9,"range":"+46.3 to +113.2"}]},{"season":"winter","values":[{"year":1960,"delta":3385.8,"range":"+3167.3 to +3652.7"},{"year":1970,"delta":3356.4,"range":"+3031.7 to +3656.6"},{"year":1980,"delta":3326.2,"range":"+3073.3 to +3523.5"},{"year":1990,"delta":3045,"range":"+2673.6 to +3432.2"},{"year":2000,"delta":3253.2,"range":"+2922.4 to +3457.7"}]}]}},{"type":"Feature","geometry":null,"properties":{"variable_name":"heatdegdays","name":"Westfield","uid":null,"data":[{"season":"annual","values":[{"year":1960,"delta":7927.8,"range":"+7650.4 to +8343.9"},{"year":1970,"delta":7737.5,"range":"+7114.6 to +8227.2"},{"year":1980,"delta":7674.5,"range":"+7480.2 to +7977.7"},{"year":1990,"delta":7446.5,"range":"+6580.7 to +8052.4"},{"year":2000,"delta":7462.3,"range":"+7035.5 to +7808.6"}]},{"season":"fall","values":[{"year":1960,"delta":1602.3,"range":"+1424.4 to +1884.5"},{"year":1970,"delta":1596.4,"range":"+1405.8 to +1863.0"},{"year":1980,"delta":1625,"range":"+1474.9 to +1744.0"},{"year":1990,"delta":1626.3,"range":"+1403.2 to +1804.9"},{"year":2000,"delta":1535.9,"range":"+1420.2 to +1649.6"}]},{"season":"spring","values":[{"year":1960,"delta":2122.5,"range":"+1869.1 to +2423.7"},{"year":1970,"delta":2048.4,"range":"+1797.9 to +2264.4"},{"year":1980,"delta":1987.8,"range":"+1811.0 to +2301.0"},{"year":1990,"delta":2038.2,"range":"+1644.9 to +2274.9"},{"year":2000,"delta":1970.9,"range":"+1777.8 to +2185.1"}]},{"season":"summer","values":[{"year":1960,"delta":233,"range":"+120.1 to +312.9"},{"year":1970,"delta":198.9,"range":"+103.3 to +267.0"},{"year":1980,"delta":228.3,"range":"+145.8 to +311.5"},{"year":1990,"delta":183.2,"range":"+118.4 to +297.3"},{"year":2000,"delta":177.1,"range":"+96.9 to +247.3"}]},{"season":"winter","values":[{"year":1960,"delta":3969.9,"range":"+3660.9 to +4360.4"},{"year":1970,"delta":3893.9,"range":"+3600.2 to +4143.2"},{"year":1980,"delta":3833.4,"range":"+3538.9 to +4054.8"},{"year":1990,"delta":3598.9,"range":"+3147.9 to +4082.6"},{"year":2000,"delta":3778.3,"range":"+3340.4 to +4035.6"}]}]}},{"type":"Feature","geometry":null,"properties":{"variable_name":"heatdegdays","name":"Barnstable","uid":null,"data":[{"season":"spring","values":[{"year":1960,"delta":1852.6,"range":"+1707.9 to +2172.4"},{"year":1970,"delta":1757.4,"range":"+1585.3 to +1941.9"},{"year":1980,"delta":1775.2,"range":"+1665.1 to +1892.1"},{"year":1990,"delta":1754.2,"range":"+1509.4 to +2020.2"},{"year":2000,"delta":1712.8,"range":"+1565.4 to +1900.2"}]},{"season":"annual","values":[{"year":1960,"delta":6245.9,"range":"+6040.4 to +6465.4"},{"year":1970,"delta":6068.4,"range":"+5640.7 to +6428.2"},{"year":1980,"delta":6073.8,"range":"+5692.9 to +6430.6"},{"year":1990,"delta":5737.4,"range":"+5180.7 to +6331.0"},{"year":2000,"delta":5765.2,"range":"+5347.7 to +6051.3"}]},{"season":"fall","values":[{"year":1960,"delta":1150.3,"range":"+977.4 to +1287.9"},{"year":1970,"delta":1130.9,"range":"+934.4 to +1344.0"},{"year":1980,"delta":1117.1,"range":"+939.4 to +1226.0"},{"year":1990,"delta":1070.3,"range":"+959.6 to +1215.0"},{"year":2000,"delta":1007.9,"range":"+892.1 to +1136.4"}]},{"season":"winter","values":[{"year":1960,"delta":3140.4,"range":"+2939.3 to +3431.4"},{"year":1970,"delta":3085.1,"range":"+2805.9 to +3376.2"},{"year":1980,"delta":3073.5,"range":"+2689.7 to +3302.7"},{"year":1990,"delta":2832.4,"range":"+2470.4 to +3123.3"},{"year":2000,"delta":2952.7,"range":"+2670.5 to +3209.7"}]},{"season":"summer","values":[{"year":1960,"delta":102.5,"range":"+64.5 to +137.3"},{"year":1970,"delta":95,"range":"+49.5 to +125.2"},{"year":1980,"delta":108,"range":"+35.8 to +204.6"},{"year":1990,"delta":80.5,"range":"+48.5 to +126.3"},{"year":2000,"delta":91.7,"range":"+34.7 to +122.0"}]}]}},{"type":"Feature","geometry":null,"properties":{"variable_name":"heatdegdays","name":"Berkshire","uid":null,"data":[{"season":"summer","values":[{"year":1960,"delta":277.4,"range":"+155.4 to +368.7"},{"year":1970,"delta":258.8,"range":"+138.6 to +339.1"},{"year":1980,"delta":274.9,"range":"+208.0 to +380.8"},{"year":1990,"delta":207.4,"range":"+137.2 to +338.4"},{"year":2000,"delta":194,"range":"+99.9 to +273.4"}]},{"season":"spring","values":[{"year":1960,"delta":2199.3,"range":"+1968.2 to +2529.6"},{"year":1970,"delta":2171.9,"range":"+1952.2 to +2420.2"},{"year":1980,"delta":2090.3,"range":"+1909.0 to +2379.2"},{"year":1990,"delta":2107.2,"range":"+1750.2 to +2365.4"},{"year":2000,"delta":2030.2,"range":"+1809.5 to +2263.7"}]},{"season":"fall","values":[{"year":1960,"delta":1685.3,"range":"+1464.1 to +1920.7"},{"year":1970,"delta":1726.1,"range":"+1517.5 to +2020.4"},{"year":1980,"delta":1733.1,"range":"+1561.0 to +1854.2"},{"year":1990,"delta":1711.3,"range":"+1496.2 to +1897.4"},{"year":2000,"delta":1589.8,"range":"+1453.9 to +1722.8"}]},{"season":"annual","values":[{"year":1960,"delta":8207.5,"range":"+8029.0 to +8452.5"},{"year":1970,"delta":8180.3,"range":"+7539.3 to +8647.6"},{"year":1980,"delta":8065.3,"range":"+7810.5 to +8353.9"},{"year":1990,"delta":7740.1,"range":"+6800.5 to +8296.3"},{"year":2000,"delta":7681.4,"range":"+7275.4 to +8061.3"}]},{"season":"winter","values":[{"year":1960,"delta":4045.5,"range":"+3758.2 to +4379.9"},{"year":1970,"delta":4023.5,"range":"+3736.8 to +4293.6"},{"year":1980,"delta":3967,"range":"+3636.7 to +4203.2"},{"year":1990,"delta":3714.1,"range":"+3248.3 to +4184.0"},{"year":2000,"delta":3867.4,"range":"+3425.4 to +4153.5"}]}]}},{"type":"Feature","geometry":null,"properties":{"variable_name":"heatdegdays","name":"Bristol","uid":null,"data":[{"season":"summer","values":[{"year":1960,"delta":72,"range":"+31.4 to +123.9"},{"year":1970,"delta":73.9,"range":"+27.7 to +102.2"},{"year":1980,"delta":88.1,"range":"+36.5 to +184.0"},{"year":1990,"delta":47.8,"range":"+19.9 to +96.1"},{"year":2000,"delta":69.6,"range":"+32.6 to +95.9"}]},{"season":"spring","values":[{"year":1960,"delta":1695.6,"range":"+1579.5 to +2025.6"},{"year":1970,"delta":1616.9,"range":"+1418.1 to +1817.0"},{"year":1980,"delta":1624.6,"range":"+1508.7 to +1839.8"},{"year":1990,"delta":1592.7,"range":"+1312.9 to +1820.3"},{"year":2000,"delta":1626.6,"range":"+1474.9 to +1841.8"}]},{"season":"fall","values":[{"year":1960,"delta":1138.5,"range":"+956.8 to +1285.9"},{"year":1970,"delta":1163.1,"range":"+922.9 to +1422.9"},{"year":1980,"delta":1180.9,"range":"+997.3 to +1345.1"},{"year":1990,"delta":1116,"range":"+948.4 to +1296.9"},{"year":2000,"delta":1087.8,"range":"+913.0 to +1183.8"}]},{"season":"annual","values":[{"year":1960,"delta":6128.5,"range":"+5892.0 to +6392.3"},{"year":1970,"delta":6026.6,"range":"+5461.5 to +6575.9"},{"year":1980,"delta":6092.3,"range":"+5870.1 to +6446.8"},{"year":1990,"delta":5695.3,"range":"+5070.9 to +6174.2"},{"year":2000,"delta":5915.9,"range":"+5446.4 to +6304.2"}]},{"season":"winter","values":[{"year":1960,"delta":3222.4,"range":"+3024.0 to +3491.5"},{"year":1970,"delta":3172.8,"range":"+2878.9 to +3448.5"},{"year":1980,"delta":3198.8,"range":"+2911.3 to +3402.8"},{"year":1990,"delta":2938.8,"range":"+2564.8 to +3297.7"},{"year":2000,"delta":3131.9,"range":"+2793.0 to +3369.4"}]}]}},{"type":"Feature","geometry":null,"properties":{"variable_name":"heatdegdays","name":"Dukes","uid":null,"data":[{"season":"summer","values":[{"year":1960,"delta":94.4,"range":"+70.9 to +115.8"},{"year":1970,"delta":73.9,"range":"+33.3 to +93.4"},{"year":1980,"delta":92.5,"range":"+20.4 to +214.0"},{"year":1990,"delta":62.6,"range":"+30.9 to +103.1"},{"year":2000,"delta":78.3,"range":"+32.9 to +100.7"}]},{"season":"annual","values":[{"year":1960,"delta":6158,"range":"+5870.2 to +6438.1"},{"year":1970,"delta":5840.6,"range":"+5393.7 to +6267.2"},{"year":1980,"delta":5950.9,"range":"+5630.2 to +6252.4"},{"year":1990,"delta":5524.8,"range":"+4983.3 to +6141.4"},{"year":2000,"delta":5549.2,"range":"+5116.9 to +5906.0"}]},{"season":"fall","values":[{"year":1960,"delta":1075,"range":"+905.4 to +1210.5"},{"year":1970,"delta":1031.6,"range":"+816.9 to +1265.6"},{"year":1980,"delta":1089.6,"range":"+922.6 to +1199.1"},{"year":1990,"delta":1004,"range":"+822.2 to +1168.6"},{"year":2000,"delta":924,"range":"+774.2 to +1035.8"}]},{"season":"spring","values":[{"year":1960,"delta":1852.2,"range":"+1702.0 to +2139.1"},{"year":1970,"delta":1704,"range":"+1533.7 to +1888.3"},{"year":1980,"delta":1721.2,"range":"+1574.3 to +1859.3"},{"year":1990,"delta":1686.4,"range":"+1438.3 to +1983.8"},{"year":2000,"delta":1654.8,"range":"+1491.6 to +1845.6"}]},{"season":"winter","values":[{"year":1960,"delta":3136.5,"range":"+2886.3 to +3402.0"},{"year":1970,"delta":3031.1,"range":"+2729.5 to +3336.2"},{"year":1980,"delta":3047.6,"range":"+2682.9 to +3260.3"},{"year":1990,"delta":2771.8,"range":"+2411.0 to +3043.3"},{"year":2000,"delta":2892.1,"range":"+2578.5 to +3137.4"}]}]}},{"type":"Feature","geometry":null,"properties":{"variable_name":"heatdegdays","name":"Essex","uid":null,"data":[{"season":"spring","values":[{"year":1960,"delta":1760.8,"range":"+1632.2 to +2105.2"},{"year":1970,"delta":1663.5,"range":"+1415.8 to +1916.1"},{"year":1980,"delta":1713.9,"range":"+1549.8 to +1914.0"},{"year":1990,"delta":1726.8,"range":"+1458.3 to +1974.4"},{"year":2000,"delta":1696.2,"range":"+1526.4 to +1900.2"}]},{"season":"fall","values":[{"year":1960,"delta":1210.3,"range":"+1030.7 to +1351.9"},{"year":1970,"delta":1218.5,"range":"+1013.6 to +1405.3"},{"year":1980,"delta":1300.3,"range":"+1180.7 to +1426.1"},{"year":1990,"delta":1241.8,"range":"+1046.5 to +1458.4"},{"year":2000,"delta":1164.6,"range":"+1015.7 to +1291.8"}]},{"season":"annual","values":[{"year":1960,"delta":6442.8,"range":"+6186.9 to +6694.9"},{"year":1970,"delta":6306.2,"range":"+5853.5 to +6722.8"},{"year":1980,"delta":6479.9,"range":"+6145.8 to +6836.0"},{"year":1990,"delta":6181.5,"range":"+5414.0 to +6795.4"},{"year":2000,"delta":6218.5,"range":"+5817.7 to +6647.0"}]},{"season":"winter","values":[{"year":1960,"delta":3386.3,"range":"+3194.7 to +3678.6"},{"year":1970,"delta":3347.1,"range":"+3051.0 to +3601.5"},{"year":1980,"delta":3348.1,"range":"+3055.7 to +3546.3"},{"year":1990,"delta":3139.8,"range":"+2752.1 to +3545.3"},{"year":2000,"delta":3272,"range":"+2905.0 to +3521.6"}]},{"season":"summer","values":[{"year":1960,"delta":85.3,"range":"+56.1 to +143.0"},{"year":1970,"delta":77.2,"range":"+42.9 to +97.7"},{"year":1980,"delta":117.5,"range":"+56.3 to +215.3"},{"year":1990,"delta":73.2,"range":"+33.1 to +109.2"},{"year":2000,"delta":85.8,"range":"+50.3 to +117.1"}]}]}},{"type":"Feature","geometry":null,"properties":{"variable_name":"heatdegdays","name":"Franklin","uid":null,"data":[{"season":"fall","values":[{"year":1960,"delta":1586.3,"range":"+1364.4 to +1805.6"},{"year":1970,"delta":1591.1,"range":"+1407.2 to +1841.6"},{"year":1980,"delta":1610,"range":"+1456.3 to +1759.2"},{"year":1990,"delta":1608.5,"range":"+1362.5 to +1772.5"},{"year":2000,"delta":1536.6,"range":"+1438.5 to +1625.8"}]},{"season":"winter","values":[{"year":1960,"delta":3979.1,"range":"+3740.5 to +4315.4"},{"year":1970,"delta":3919.6,"range":"+3629.3 to +4223.1"},{"year":1980,"delta":3856.7,"range":"+3578.8 to +4053.8"},{"year":1990,"delta":3625.5,"range":"+3174.4 to +4136.5"},{"year":2000,"delta":3829.1,"range":"+3423.8 to +4075.7"}]},{"season":"annual","values":[{"year":1960,"delta":7861,"range":"+7618.4 to +8146.1"},{"year":1970,"delta":7681.7,"range":"+7102.2 to +8113.2"},{"year":1980,"delta":7618.5,"range":"+7381.3 to +7962.6"},{"year":1990,"delta":7375.1,"range":"+6579.1 to +7967.9"},{"year":2000,"delta":7523.7,"range":"+7163.5 to +7906.4"}]},{"season":"summer","values":[{"year":1960,"delta":202.1,"range":"+105.0 to +285.5"},{"year":1970,"delta":170.5,"range":"+80.7 to +232.2"},{"year":1980,"delta":201.3,"range":"+136.9 to +278.2"},{"year":1990,"delta":148.8,"range":"+105.6 to +245.1"},{"year":2000,"delta":167.2,"range":"+89.6 to +224.4"}]},{"season":"spring","values":[{"year":1960,"delta":2093.5,"range":"+1869.0 to +2443.5"},{"year":1970,"delta":2000.5,"range":"+1742.5 to +2239.7"},{"year":1980,"delta":1950.6,"range":"+1765.1 to +2243.2"},{"year":1990,"delta":1992.3,"range":"+1593.6 to +2248.8"},{"year":2000,"delta":1990.8,"range":"+1790.7 to +2189.0"}]}]}},{"type":"Feature","geometry":null,"properties":{"variable_name":"heatdegdays","name":"Hampden","uid":null,"data":[{"season":"spring","values":[{"year":1960,"delta":1891,"range":"+1687.5 to +2238.1"},{"year":1970,"delta":1826.6,"range":"+1563.4 to +2064.9"},{"year":1980,"delta":1789.4,"range":"+1636.9 to +2100.0"},{"year":1990,"delta":1854.2,"range":"+1508.1 to +2059.6"},{"year":2000,"delta":1807.6,"range":"+1637.8 to +1996.2"}]},{"season":"fall","values":[{"year":1960,"delta":1405.1,"range":"+1178.6 to +1608.0"},{"year":1970,"delta":1403.3,"range":"+1192.2 to +1634.0"},{"year":1980,"delta":1460.1,"range":"+1341.3 to +1580.3"},{"year":1990,"delta":1447,"range":"+1240.4 to +1637.1"},{"year":2000,"delta":1355.4,"range":"+1245.2 to +1466.7"}]},{"season":"annual","values":[{"year":1960,"delta":7143.6,"range":"+6857.7 to +7388.8"},{"year":1970,"delta":7013,"range":"+6361.9 to +7622.0"},{"year":1980,"delta":7026.8,"range":"+6767.7 to +7326.8"},{"year":1990,"delta":6794,"range":"+5968.6 to +7389.3"},{"year":2000,"delta":6841.7,"range":"+6493.1 to +7162.3"}]},{"season":"summer","values":[{"year":1960,"delta":131,"range":"+69.1 to +214.3"},{"year":1970,"delta":118.3,"range":"+51.9 to +170.2"},{"year":1980,"delta":145.5,"range":"+67.2 to +213.0"},{"year":1990,"delta":111,"range":"+69.2 to +197.3"},{"year":2000,"delta":117.8,"range":"+67.0 to +165.3"}]},{"season":"winter","values":[{"year":1960,"delta":3716.5,"range":"+3484.7 to +4062.9"},{"year":1970,"delta":3664.8,"range":"+3331.0 to +3931.0"},{"year":1980,"delta":3631.7,"range":"+3346.6 to +3843.2"},{"year":1990,"delta":3381.9,"range":"+2933.8 to +3852.3"},{"year":2000,"delta":3560.9,"range":"+3161.5 to +3808.4"}]}]}},{"type":"Feature","geometry":null,"properties":{"variable_name":"heatdegdays","name":"Hampshire","uid":null,"data":[{"season":"annual","values":[{"year":1960,"delta":7564.4,"range":"+7254.0 to +7978.2"},{"year":1970,"delta":7299.1,"range":"+6719.4 to +7705.1"},{"year":1980,"delta":7301.3,"range":"+7082.6 to +7683.7"},{"year":1990,"delta":7140.6,"range":"+6298.1 to +7753.8"},{"year":2000,"delta":7244.9,"range":"+6915.8 to +7587.0"}]},{"season":"winter","values":[{"year":1960,"delta":3876.1,"range":"+3562.3 to +4252.6"},{"year":1970,"delta":3766.6,"range":"+3467.3 to +4054.7"},{"year":1980,"delta":3715.8,"range":"+3455.1 to +3918.7"},{"year":1990,"delta":3510,"range":"+3053.5 to +4017.1"},{"year":2000,"delta":3718,"range":"+3310.4 to +3939.1"}]},{"season":"summer","values":[{"year":1960,"delta":173.3,"range":"+78.1 to +252.7"},{"year":1970,"delta":145.3,"range":"+67.2 to +198.9"},{"year":1980,"delta":179,"range":"+110.3 to +240.5"},{"year":1990,"delta":142.8,"range":"+96.0 to +242.7"},{"year":2000,"delta":149.9,"range":"+77.7 to +203.4"}]},{"season":"spring","values":[{"year":1960,"delta":2017,"range":"+1755.1 to +2316.6"},{"year":1970,"delta":1901,"range":"+1630.0 to +2121.4"},{"year":1980,"delta":1874.4,"range":"+1678.7 to +2215.6"},{"year":1990,"delta":1936.9,"range":"+1513.4 to +2185.4"},{"year":2000,"delta":1912.4,"range":"+1707.8 to +2095.2"}]},{"season":"fall","values":[{"year":1960,"delta":1498,"range":"+1334.3 to +1772.1"},{"year":1970,"delta":1486.1,"range":"+1296.3 to +1719.1"},{"year":1980,"delta":1532.1,"range":"+1386.9 to +1688.9"},{"year":1990,"delta":1550.8,"range":"+1293.2 to +1734.1"},{"year":2000,"delta":1464.6,"range":"+1345.7 to +1576.7"}]}]}},{"type":"Feature","geometry":null,"properties":{"variable_name":"heatdegdays","name":"Middlesex","uid":null,"data":[{"season":"annual","values":[{"year":1960,"delta":6700,"range":"+6410.1 to +6988.3"},{"year":1970,"delta":6701.5,"range":"+6170.1 to +7114.9"},{"year":1980,"delta":6701,"range":"+6416.9 to +7061.7"},{"year":1990,"delta":6389.7,"range":"+5602.8 to +6935.9"},{"year":2000,"delta":6522.2,"range":"+6172.3 to +6897.1"}]},{"season":"fall","values":[{"year":1960,"delta":1289.5,"range":"+1089.7 to +1463.6"},{"year":1970,"delta":1352.2,"range":"+1163.1 to +1552.9"},{"year":1980,"delta":1375.8,"range":"+1231.1 to +1524.3"},{"year":1990,"delta":1328.2,"range":"+1145.8 to +1510.7"},{"year":2000,"delta":1262.2,"range":"+1141.8 to +1359.5"}]},{"season":"winter","values":[{"year":1960,"delta":3518.2,"range":"+3312.5 to +3809.0"},{"year":1970,"delta":3514.2,"range":"+3203.4 to +3779.2"},{"year":1980,"delta":3487.6,"range":"+3220.2 to +3672.6"},{"year":1990,"delta":3257.3,"range":"+2838.5 to +3683.0"},{"year":2000,"delta":3427,"range":"+3050.1 to +3647.1"}]},{"season":"summer","values":[{"year":1960,"delta":94.3,"range":"+54.1 to +150.9"},{"year":1970,"delta":99.1,"range":"+48.7 to +126.0"},{"year":1980,"delta":120.4,"range":"+61.4 to +203.3"},{"year":1990,"delta":72.7,"range":"+32.0 to +112.9"},{"year":2000,"delta":93,"range":"+61.5 to +117.5"}]},{"season":"spring","values":[{"year":1960,"delta":1798,"range":"+1645.2 to +2136.5"},{"year":1970,"delta":1736,"range":"+1486.8 to +1987.6"},{"year":1980,"delta":1717.2,"range":"+1568.3 to +1955.5"},{"year":1990,"delta":1731.6,"range":"+1435.9 to +1950.2"},{"year":2000,"delta":1740,"range":"+1576.5 to +1922.1"}]}]}},{"type":"Feature","geometry":null,"properties":{"variable_name":"heatdegdays","name":"Nantucket","uid":null,"data":[{"season":"annual","values":[{"year":1960,"delta":6220.2,"range":"+5955.8 to +6490.5"},{"year":1970,"delta":5899,"range":"+5486.6 to +6079.4"},{"year":1980,"delta":5796.4,"range":"+5653.0 to +6124.7"},{"year":1990,"delta":5836.5,"range":"+5708.8 to +6224.0"},{"year":2000,"delta":5861.8,"range":"+5738.9 to +5925.8"}]},{"season":"summer","values":[{"year":1960,"delta":156.2,"range":"+112.8 to +217.0"},{"year":1970,"delta":140,"range":"+101.0 to +208.5"},{"year":1980,"delta":110.9,"range":"+69.9 to +242.4"},{"year":1990,"delta":73.6,"range":"+48.7 to +121.0"},{"year":2000,"delta":104.6,"range":"+90.8 to +115.1"}]},{"season":"spring","values":[{"year":1960,"delta":2005.3,"range":"+1831.8 to +2262.5"},{"year":1970,"delta":1831.2,"range":"+1605.8 to +2084.8"},{"year":1980,"delta":1735.4,"range":"+1633.9 to +1893.3"},{"year":1990,"delta":1807,"range":"+1700.9 to +2015.6"},{"year":2000,"delta":1806.5,"range":"+1683.3 to +1897.0"}]},{"season":"fall","values":[{"year":1960,"delta":1134,"range":"+951.6 to +1297.9"},{"year":1970,"delta":1080.8,"range":"+728.7 to +1261.5"},{"year":1980,"delta":1054.3,"range":"+912.9 to +1188.7"},{"year":1990,"delta":1048.1,"range":"+915.1 to +1139.4"},{"year":2000,"delta":919.1,"range":"+842.1 to +977.6"}]},{"season":"winter","values":[{"year":1960,"delta":2949.9,"range":"+2788.8 to +3134.0"},{"year":1970,"delta":2920.8,"range":"+2653.3 to +3170.8"},{"year":1980,"delta":2899.6,"range":"+2658.4 to +3120.3"},{"year":1990,"delta":2884.4,"range":"+2752.1 to +3034.1"},{"year":2000,"delta":2970,"range":"+2604.8 to +3149.8"}]}]}},{"type":"Feature","geometry":null,"properties":{"variable_name":"heatdegdays","name":"Norfolk","uid":null,"data":[{"season":"annual","values":[{"year":1960,"delta":6507.5,"range":"+6332.8 to +6743.1"},{"year":1970,"delta":6389.5,"range":"+5795.4 to +6840.8"},{"year":1980,"delta":6361.4,"range":"+6141.4 to +6701.5"},{"year":1990,"delta":5979.5,"range":"+5312.5 to +6501.6"},{"year":2000,"delta":6108.1,"range":"+5690.1 to +6501.0"}]},{"season":"winter","values":[{"year":1960,"delta":3397.5,"range":"+3177.6 to +3677.3"},{"year":1970,"delta":3364.6,"range":"+3034.2 to +3672.8"},{"year":1980,"delta":3328.9,"range":"+3058.7 to +3534.7"},{"year":1990,"delta":3062.5,"range":"+2684.3 to +3438.8"},{"year":2000,"delta":3235.4,"range":"+2888.2 to +3456.7"}]},{"season":"summer","values":[{"year":1960,"delta":98.7,"range":"+53.3 to +156.2"},{"year":1970,"delta":88.4,"range":"+34.3 to +114.8"},{"year":1980,"delta":102.6,"range":"+46.2 to +177.8"},{"year":1990,"delta":61.6,"range":"+25.4 to +103.7"},{"year":2000,"delta":79.9,"range":"+43.8 to +110.3"}]},{"season":"spring","values":[{"year":1960,"delta":1768.9,"range":"+1627.1 to +2087.8"},{"year":1970,"delta":1675.2,"range":"+1413.3 to +1913.6"},{"year":1980,"delta":1656.9,"range":"+1541.3 to +1907.7"},{"year":1990,"delta":1641.8,"range":"+1363.8 to +1865.2"},{"year":2000,"delta":1646.9,"range":"+1493.8 to +1839.4"}]},{"season":"fall","values":[{"year":1960,"delta":1242.4,"range":"+1069.1 to +1392.8"},{"year":1970,"delta":1261.3,"range":"+1052.1 to +1477.2"},{"year":1980,"delta":1273,"range":"+1117.0 to +1424.0"},{"year":1990,"delta":1213.6,"range":"+1037.5 to +1384.3"},{"year":2000,"delta":1145.9,"range":"+989.6 to +1267.3"}]}]}},{"type":"Feature","geometry":null,"properties":{"variable_name":"heatdegdays","name":"Plymouth","uid":null,"data":[{"season":"summer","values":[{"year":1960,"delta":94.6,"range":"+48.4 to +144.7"},{"year":1970,"delta":95.7,"range":"+41.7 to +124.5"},{"year":1980,"delta":104.7,"range":"+46.6 to +200.5"},{"year":1990,"delta":63,"range":"+31.9 to +113.9"},{"year":2000,"delta":81.4,"range":"+39.3 to +104.9"}]},{"season":"fall","values":[{"year":1960,"delta":1212.4,"range":"+1010.0 to +1367.8"},{"year":1970,"delta":1242.8,"range":"+1047.0 to +1464.4"},{"year":1980,"delta":1218.2,"range":"+1055.2 to +1359.3"},{"year":1990,"delta":1122.3,"range":"+953.4 to +1295.9"},{"year":2000,"delta":1093,"range":"+945.1 to +1193.5"}]},{"season":"annual","values":[{"year":1960,"delta":6366.2,"range":"+6047.8 to +6741.2"},{"year":1970,"delta":6328.7,"range":"+5797.7 to +6802.3"},{"year":1980,"delta":6267.8,"range":"+5982.6 to +6663.4"},{"year":1990,"delta":5746.8,"range":"+5152.0 to +6270.4"},{"year":2000,"delta":5944.4,"range":"+5460.2 to +6382.6"}]},{"season":"spring","values":[{"year":1960,"delta":1786.2,"range":"+1648.1 to +2151.7"},{"year":1970,"delta":1723.3,"range":"+1523.4 to +1940.1"},{"year":1980,"delta":1710.4,"range":"+1588.7 to +1897.3"},{"year":1990,"delta":1639.3,"range":"+1357.1 to +1880.2"},{"year":2000,"delta":1667.5,"range":"+1487.9 to +1883.7"}]},{"season":"winter","values":[{"year":1960,"delta":3273,"range":"+3130.1 to +3588.1"},{"year":1970,"delta":3267,"range":"+2973.2 to +3548.5"},{"year":1980,"delta":3234.4,"range":"+2899.8 to +3462.2"},{"year":1990,"delta":2922.3,"range":"+2566.8 to +3248.8"},{"year":2000,"delta":3102.4,"range":"+2782.4 to +3336.5"}]}]}},{"type":"Feature","geometry":null,"properties":{"variable_name":"heatdegdays","name":"Suffolk","uid":null,"data":[{"season":"fall","values":[{"year":1960,"delta":1089.8,"range":"+927.9 to +1231.7"},{"year":1970,"delta":1144.9,"range":"+905.9 to +1338.9"},{"year":1980,"delta":1154.9,"range":"+970.5 to +1310.2"},{"year":1990,"delta":1122.4,"range":"+951.9 to +1297.7"},{"year":2000,"delta":1058.6,"range":"+914.7 to +1189.7"}]},{"season":"annual","values":[{"year":1960,"delta":6063.4,"range":"+5890.1 to +6334.5"},{"year":1970,"delta":6058.4,"range":"+5584.3 to +6428.5"},{"year":1980,"delta":6065,"range":"+5828.1 to +6431.8"},{"year":1990,"delta":5771.6,"range":"+5140.9 to +6326.3"},{"year":2000,"delta":5885.9,"range":"+5476.2 to +6287.8"}]},{"season":"winter","values":[{"year":1960,"delta":3248,"range":"+3055.7 to +3515.8"},{"year":1970,"delta":3250.7,"range":"+2959.8 to +3490.4"},{"year":1980,"delta":3227.9,"range":"+3001.8 to +3451.0"},{"year":1990,"delta":2999.2,"range":"+2636.7 to +3352.7"},{"year":2000,"delta":3141.1,"range":"+2788.2 to +3363.8"}]},{"season":"summer","values":[{"year":1960,"delta":62.3,"range":"+30.8 to +106.9"},{"year":1970,"delta":60.7,"range":"+32.5 to +80.5"},{"year":1980,"delta":81.2,"range":"+24.4 to +161.3"},{"year":1990,"delta":48.4,"range":"+16.2 to +85.0"},{"year":2000,"delta":70.1,"range":"+30.2 to +92.1"}]},{"season":"spring","values":[{"year":1960,"delta":1663.4,"range":"+1507.7 to +1991.1"},{"year":1970,"delta":1602.1,"range":"+1325.9 to +1843.4"},{"year":1980,"delta":1601,"range":"+1446.9 to +1862.3"},{"year":1990,"delta":1601.6,"range":"+1322.2 to +1838.6"},{"year":2000,"delta":1616.2,"range":"+1447.0 to +1807.9"}]}]}},{"type":"Feature","geometry":null,"properties":{"variable_name":"heatdegdays","name":"Worcester","uid":null,"data":[{"season":"fall","values":[{"year":1960,"delta":1434.7,"range":"+1222.9 to +1612.7"},{"year":1970,"delta":1501.9,"range":"+1330.1 to +1763.6"},{"year":1980,"delta":1522.2,"range":"+1385.3 to +1656.6"},{"year":1990,"delta":1460.1,"range":"+1278.4 to +1640.6"},{"year":2000,"delta":1394.1,"range":"+1267.9 to +1519.2"}]},{"season":"winter","values":[{"year":1960,"delta":3743.1,"range":"+3520.8 to +4056.4"},{"year":1970,"delta":3723.7,"range":"+3402.1 to +4021.0"},{"year":1980,"delta":3696.7,"range":"+3411.4 to +3899.5"},{"year":1990,"delta":3399.9,"range":"+2955.9 to +3835.4"},{"year":2000,"delta":3606.3,"range":"+3249.6 to +3877.8"}]},{"season":"annual","values":[{"year":1960,"delta":7287.3,"range":"+7091.1 to +7500.4"},{"year":1970,"delta":7274.2,"range":"+6672.4 to +7671.0"},{"year":1980,"delta":7269.3,"range":"+6963.3 to +7579.4"},{"year":1990,"delta":6853.4,"range":"+6043.2 to +7412.5"},{"year":2000,"delta":7015.9,"range":"+6631.8 to +7505.6"}]},{"season":"summer","values":[{"year":1960,"delta":150.9,"range":"+96.2 to +224.8"},{"year":1970,"delta":151.6,"range":"+73.8 to +197.2"},{"year":1980,"delta":177.4,"range":"+116.2 to +259.2"},{"year":1990,"delta":117.6,"range":"+72.1 to +193.2"},{"year":2000,"delta":141.6,"range":"+83.5 to +175.0"}]},{"season":"spring","values":[{"year":1960,"delta":1958.5,"range":"+1782.8 to +2328.0"},{"year":1970,"delta":1896.9,"range":"+1633.7 to +2134.9"},{"year":1980,"delta":1873,"range":"+1728.9 to +2126.5"},{"year":1990,"delta":1875.8,"range":"+1565.8 to +2100.6"},{"year":2000,"delta":1873.8,"range":"+1687.7 to +2069.0"}]}]}},{"type":"Feature","geometry":null,"properties":{"variable_name":"heatdegdays","name":"Massachusetts","uid":null,"data":[{"season":"fall","values":[{"year":1960,"delta":1374.5,"range":"+1175.3 to +1557.8"},{"year":1970,"delta":1402.1,"range":"+1210.4 to +1641.0"},{"year":1980,"delta":1424.4,"range":"+1283.1 to +1557.8"},{"year":1990,"delta":1381.2,"range":"+1197.5 to +1552.5"},{"year":2000,"delta":1309.9,"range":"+1183.9 to +1413.8"}]},{"season":"summer","values":[{"year":1960,"delta":142.8,"range":"+92.5 to +208.1"},{"year":1970,"delta":133.8,"range":"+65.0 to +175.2"},{"year":1980,"delta":156.1,"range":"+93.3 to +240.2"},{"year":1990,"delta":108.4,"range":"+69.7 to +171.1"},{"year":2000,"delta":122.1,"range":"+79.2 to +151.9"}]},{"season":"annual","values":[{"year":1960,"delta":7047.6,"range":"+6865.3 to +7273.3"},{"year":1970,"delta":6956.7,"range":"+6393.7 to +7387.7"},{"year":1980,"delta":6949.8,"range":"+6691.1 to +7278.4"},{"year":1990,"delta":6609.7,"range":"+5852.0 to +7157.9"},{"year":2000,"delta":6716.3,"range":"+6341.8 to +7111.9"}]},{"season":"winter","values":[{"year":1960,"delta":3615.7,"range":"+3391.6 to +3902.0"},{"year":1970,"delta":3579.3,"range":"+3279.7 to +3857.7"},{"year":1980,"delta":3550.2,"range":"+3253.9 to +3753.5"},{"year":1990,"delta":3294,"range":"+2876.3 to +3715.6"},{"year":2000,"delta":3471.7,"range":"+3100.9 to +3703.9"}]},{"season":"spring","values":[{"year":1960,"delta":1914.7,"range":"+1745.8 to +2256.5"},{"year":1970,"delta":1841.6,"range":"+1603.6 to +2066.3"},{"year":1980,"delta":1819.2,"range":"+1681.4 to +2067.8"},{"year":1990,"delta":1826.1,"range":"+1507.3 to +2033.9"},{"year":2000,"delta":1812.6,"range":"+1654.7 to +2009.6"}]}]}}]}
